equations_solvers-0.1.1.dist-info/licenses/LICENCE.txt
matrices/__init__.py
matrices/matrices2x2.py
matrices/matrices3x3.py
tests/__init__.py
tests/test_linear_equations_solver.py
tests/test_matrices2x2.py
tests/test_matrices3x3.py
equations_solvers-0.1.1.dist-info/METADATA
equations_solvers-0.1.1.dist-info/WHEEL
equations_solvers-0.1.1.dist-info/top_level.txt
equations_solvers-0.1.1.dist-info/RECORD
