Metadata-Version: 2.4
Name: equations_solvers
Version: 0.1.1
Summary: A Python package for matrix operations and solving linear equations
Home-page: https://github.com/hammailriaz/Equations_Solvers
Author: Hammail Riaz
Author-email: Hammail Riaz <hammailriaz.dev@gmail.com>
License: MIT
Project-URL: Homepage, https://github.com/Hammail-Riaz/equations_solvers
Project-URL: Documentation, https://github.com/Hammail-Riaz/equations_solvers#readme
Project-URL: Repository, https://github.com/Hammail-Riaz/equations_solvers
Keywords: matrix,linear-equations,mathematics,algebra
Classifier: Development Status :: 4 - Beta
Classifier: Intended Audience :: Developers
Classifier: Intended Audience :: Education
Classifier: License :: OSI Approved :: MIT License
Classifier: Programming Language :: Python :: 3
Classifier: Programming Language :: Python :: 3.8
Classifier: Programming Language :: Python :: 3.9
Classifier: Programming Language :: Python :: 3.10
Classifier: Programming Language :: Python :: 3.11
Classifier: Programming Language :: Python :: 3.12
Classifier: Topic :: Scientific/Engineering :: Mathematics
Requires-Python: >=3.7
License-File: LICENCE.txt
Dynamic: author
Dynamic: home-page
Dynamic: license-file
Dynamic: requires-python
